fakeriak/__init__.py
fakeriak/storage.py
fakeriak/transport.py
fakeriak-0.2.dist-info/DESCRIPTION.rst
fakeriak-0.2.dist-info/METADATA
fakeriak-0.2.dist-info/RECORD
fakeriak-0.2.dist-info/WHEEL
fakeriak-0.2.dist-info/metadata.json
fakeriak-0.2.dist-info/top_level.txt
