Metadata-Version: 2.0
Name: fakeriak
Version: 0.2
Summary: Library for testing code that uses Riak.
Home-page: https://github.com/Tinche/fakeriak
Author: Tin Tvrtkovic
Author-email: tinchester@gmail.com
License: Apache 2.0
Platform: UNKNOWN
Classifier: Development Status :: 4 - Beta
Classifier: Intended Audience :: Developers
Classifier: License :: OSI Approved :: Apache Software License
Classifier: Programming Language :: Python :: 3.3
Classifier: Programming Language :: Python :: 3.4
Classifier: Programming Language :: Python :: 3.5
Classifier: Topic :: Software Development :: Testing
Requires-Dist: riak (>=2.2.0)
